CHANGES.txt
CONTRIBUTORS.txt
MANIFEST.in
README.rst
development.ini
docker.ini
production.ini
requirements.txt
requirements_develop.txt
setup.cfg
setup.py
tox.ini
papaye/__init__.py
papaye/authentification.py
papaye/bundles.py
papaye/factories.py
papaye/models.py
papaye/proxy.py
papaye/schemas.py
papaye/serializers.py
papaye.egg-info/PKG-INFO
papaye.egg-info/SOURCES.txt
papaye.egg-info/dependency_links.txt
papaye.egg-info/entry_points.txt
papaye.egg-info/not-zip-safe
papaye.egg-info/requires.txt
papaye.egg-info/top_level.txt
papaye/evolve/__init__.py
papaye/evolve/evolve1.py
papaye/evolve/evolve2.py
papaye/evolve/evolve3.py
papaye/evolve/evolve4.py
papaye/evolve/evolve5.py
papaye/evolve/evolve6.py
papaye/evolve/managers.py
papaye/evolve/models/__init__.py
papaye/evolve/models/snapshot1.py
papaye/evolve/models/snapshot2.py
papaye/scripts/__init__.py
papaye/scripts/common.py
papaye/scripts/evolve.py
papaye/scripts/initialize.py
papaye/scripts/pshell.py
papaye/static/favicon.ico
papaye/static/footerbg.png
papaye/static/headerbg.png
papaye/static/ie6.css
papaye/static/middlebg.png
papaye/static/pylons.css
papaye/static/pyramid-small.png
papaye/static/pyramid.png
papaye/static/style.css
papaye/static/transparent.gif
papaye/static/gen/css/papaye.css
papaye/static/gen/js/papaye.js
papaye/static/includes/OpenSans/OpenSans-Regular-webfont.woff
papaye/static/includes/angular/angular-resource.min.js
papaye/static/includes/angular/angular-route.min.js
papaye/static/includes/angular/angular.min.js
papaye/static/includes/bootstrap/css/bootstrap-theme.css
papaye/static/includes/bootstrap/css/bootstrap-theme.css.map
papaye/static/includes/bootstrap/css/bootstrap-theme.min.css
papaye/static/includes/bootstrap/css/bootstrap.css
papaye/static/includes/bootstrap/css/bootstrap.css.map
papaye/static/includes/bootstrap/css/bootstrap.min.css
papaye/static/includes/bootstrap/fonts/glyphicons-halflings-regular.eot
papaye/static/includes/bootstrap/fonts/glyphicons-halflings-regular.svg
papaye/static/includes/bootstrap/fonts/glyphicons-halflings-regular.ttf
papaye/static/includes/bootstrap/fonts/glyphicons-halflings-regular.woff
papaye/static/includes/bootstrap/js/bootstrap.js
