Metadata-Version: 1.1
Name: papaye
Version: 0.2.2
Summary: Yet another Python Package repository (local PyPI)
Home-page: https://github.com/rcommande/papaye
Author: Romain Commandé
Author-email: commande.romain@gmail.com
License: UNKNOWN
Keywords: web wsgi bfg pylons pyramid
Platform: UNKNOWN
Classifier: Programming Language :: Python
Classifier: Programming Language :: Python :: 3.3
Classifier: Programming Language :: Python :: 3.4
Classifier: Framework :: Pyramid
Classifier: Topic :: Internet :: WWW/HTTP
Classifier: Topic :: Internet :: WWW/HTTP :: WSGI :: Application
